LICENSE
README.md
setup.cfg
setup.py
prisma_config/__init__.py
prisma_config/default_interfaces.py
prisma_config/do.py
prisma_config/pull.py
prisma_config.egg-info/PKG-INFO
prisma_config.egg-info/SOURCES.txt
prisma_config.egg-info/dependency_links.txt
prisma_config.egg-info/entry_points.txt
prisma_config.egg-info/requires.txt
prisma_config.egg-info/top_level.txt