Metadata-Version: 2.1
Name: prisma-config
Version: 6.3.1b1
Summary: Configuration exporting and Continuous Integration (CI) capable configuration importing for the Prisma SDWAN Cloud Controller.
Home-page: https://github.com/PaloAltoNetworks/prisma_config
Author: Prisma SASE Developer Support
Author-email: prisma-sase-developers@paloaltonetworks.com
License: MIT
Classifier: Development Status :: 4 - Beta
Classifier: Intended Audience :: Developers
Classifier: License :: OSI Approved :: MIT License
Classifier: Programming Language :: Python :: 2.7
Classifier: Programming Language :: Python :: 3.6
Classifier: Programming Language :: Python :: 3.7
Classifier: Programming Language :: Python :: 3.8
License-File: LICENSE
